quantum_mcp/__init__.py
quantum_mcp/__main__.py
quantum_mcp/config.py
quantum_mcp/server.py
quantum_mcp/agents/__init__.py
quantum_mcp/agents/base.py
quantum_mcp/agents/claude.py
quantum_mcp/agents/factory.py
quantum_mcp/agents/local.py
quantum_mcp/agents/openai.py
quantum_mcp/agents/protocol.py
quantum_mcp/agents/tool.py
quantum_mcp/backends/__init__.py
quantum_mcp/backends/annealing.py
quantum_mcp/backends/dwave.py
quantum_mcp/backends/exact_solver.py
quantum_mcp/backends/factory.py
quantum_mcp/backends/protocol.py
quantum_mcp/circuits/__init__.py
quantum_mcp/circuits/converters.py
quantum_mcp/circuits/kernels.py
quantum_mcp/circuits/qaoa.py
quantum_mcp/circuits/qsharp.py
quantum_mcp/circuits/vqe.py
quantum_mcp/client/__init__.py
quantum_mcp/client/exceptions.py
quantum_mcp/client/models.py
quantum_mcp/client/quantum_client.py
quantum_mcp/orchestration/__init__.py
quantum_mcp/orchestration/benchmark.py
quantum_mcp/orchestration/collective.py
quantum_mcp/orchestration/consensus.py
quantum_mcp/orchestration/decomposer.py
quantum_mcp/orchestration/dwave_router.py
quantum_mcp/orchestration/observability.py
quantum_mcp/orchestration/qaoa_router.py
quantum_mcp/orchestration/qubo.py
quantum_mcp/orchestration/router.py
quantum_mcp/orchestration/task.py
quantum_mcp/tools/__init__.py
quantum_mcp/tools/algorithm_tools.py
quantum_mcp/tools/backend_tools.py
quantum_mcp/tools/base.py
quantum_mcp/tools/circuit_tools.py
quantum_mcp/tools/job_management.py
quantum_mcp/tools/job_tools.py
quantum_mcp/tools/registration.py
quantum_mcp/tools/simulation_tools.py
quantum_mcp/tools/utility_tools.py
quantum_mcp-0.1.0.dist-info/METADATA
quantum_mcp-0.1.0.dist-info/WHEEL
quantum_mcp-0.1.0.dist-info/entry_points.txt
quantum_mcp-0.1.0.dist-info/licenses/LICENSE
quantum_mcp-0.1.0.dist-info/RECORD
