Metadata-Version: 2.4
Name: quantum-mcp
Version: 0.1.0
Summary: Quantum Computing and Multi-Agent Orchestration MCP Server for Azure Quantum
License-Expression: MIT
License-File: LICENSE
Requires-Python: >=3.11
Requires-Dist: aiohttp>=3.9.0
Requires-Dist: azure-identity>=1.15.0
Requires-Dist: azure-quantum[qiskit]>=0.28.0
Requires-Dist: mcp>=1.0.0
Requires-Dist: numpy>=1.24.0
Requires-Dist: pydantic-settings>=2.0.0
Requires-Dist: pydantic>=2.0.0
Requires-Dist: python-dotenv>=1.0.0
Requires-Dist: qiskit-aer<0.15.0,>=0.14.0
Requires-Dist: qiskit<2.0.0,>=1.0.0
Requires-Dist: qsharp>=1.0.0
Requires-Dist: scipy>=1.10.0
Requires-Dist: structlog>=23.0.0
Requires-Dist: tenacity>=8.0.0
Provides-Extra: agents
Requires-Dist: anthropic>=0.25.0; extra == 'agents'
Requires-Dist: openai>=1.0.0; extra == 'agents'
Provides-Extra: dev
Requires-Dist: mypy>=1.0.0; extra == 'dev'
Requires-Dist: pytest-asyncio>=0.21.0; extra == 'dev'
Requires-Dist: pytest-cov>=4.0.0; extra == 'dev'
Requires-Dist: pytest>=7.0.0; extra == 'dev'
Requires-Dist: ruff>=0.1.0; extra == 'dev'
Provides-Extra: dwave
Requires-Dist: dimod>=0.12.0; extra == 'dwave'
Requires-Dist: dwave-ocean-sdk>=6.0.0; extra == 'dwave'
